yuface-2023.5.1.dist-info/METADATA
yuface-2023.5.1.dist-info/LICENSE
yuface-2023.5.1.dist-info/top_level.txt
yuface-2023.5.1.dist-info/RECORD
yuface-2023.5.1.dist-info/WHEEL
yuface/yuface.cpython-311-x86_64-linux-gnu.so
yuface/libfacedetection.so.v0.0.3
yuface/__init__.py
yuface/libfacedetection.so
yuface.libs/libgomp-a34b3233.so.1.0.0
